clean_tree/__init__.py
clean_tree-0.0.0.dist-info/METADATA
clean_tree-0.0.0.dist-info/WHEEL
clean_tree-0.0.0.dist-info/top_level.txt
clean_tree-0.0.0.dist-info/RECORD
